{"note":"This file is an internal implementation detail to speed up HTML report generation. Its format can change at any time. You might be looking for the JSON report: https://coverage.rtfd.io/cmd.html#cmd-json","format":5,"version":"7.11.0","globals":"dc5928e40fbad8f945bccc725adce0e1","files":{"z_f17df59981ee31d6_problem_2_OLMo_scot_py":{"hash":"4639e513e2587616f2bb8c324718a0b6","index":{"url":"z_f17df59981ee31d6_problem_2_OLMo_scot_py.html","file":"solutions/problem_2_OLMo_scot.py","description":"","nums":{"precision":0,"n_files":1,"n_statements":5,"n_excluded":0,"n_missing":0,"n_branches":0,"n_partial_branches":0,"n_missing_branches":0}}}}}